rdf_starbase/__init__.py
rdf_starbase/ai_grounding.py
rdf_starbase/models.py
rdf_starbase/registry.py
rdf_starbase/repositories.py
rdf_starbase/repository_api.py
rdf_starbase/store.py
rdf_starbase/store_legacy.py
rdf_starbase/web.py
rdf_starbase/compat/__init__.py
rdf_starbase/compat/rdflib.py
rdf_starbase/formats/__init__.py
rdf_starbase/formats/jsonld.py
rdf_starbase/formats/ntriples.py
rdf_starbase/formats/rdfxml.py
rdf_starbase/formats/turtle.py
rdf_starbase/sparql/__init__.py
rdf_starbase/sparql/ast.py
rdf_starbase/sparql/executor.py
rdf_starbase/sparql/parser.py
rdf_starbase/storage/__init__.py
rdf_starbase/storage/executor.py
rdf_starbase/storage/facts.py
rdf_starbase/storage/lsm.py
rdf_starbase/storage/persistence.py
rdf_starbase/storage/quoted_triples.py
rdf_starbase/storage/reasoner.py
rdf_starbase/storage/terms.py
rdf_starbase-0.2.0.dist-info/METADATA
rdf_starbase-0.2.0.dist-info/WHEEL
rdf_starbase-0.2.0.dist-info/licenses/LICENSE
rdf_starbase-0.2.0.dist-info/RECORD
