Metadata-Version: 2.4
Name: rdf-starbase
Version: 0.2.0
Summary: A blazingly fast RDF-Star database powered by Polars
Project-URL: Homepage, https://github.com/ontus/rdf-starbase
Project-URL: Repository, https://github.com/ontus/rdf-starbase
Project-URL: Documentation, https://rdf-starbase.readthedocs.io
Author-email: Ontus <team@ontus.dev>
License: MIT
License-File: LICENSE
Keywords: knowledge-graph,polars,rdf,rdf-star,semantic-web
Classifier: Development Status :: 3 - Alpha
Classifier: Intended Audience :: Developers
Classifier: License :: OSI Approved :: MIT License
Classifier: Programming Language :: Python :: 3.10
Classifier: Programming Language :: Python :: 3.11
Classifier: Programming Language :: Python :: 3.12
Requires-Python: >=3.10
Requires-Dist: polars>=0.20.0
Requires-Dist: pyarrow>=14.0.0
Requires-Dist: pydantic>=2.0.0
Requires-Dist: typing-extensions>=4.8.0
Provides-Extra: dev
Requires-Dist: black>=23.0.0; extra == 'dev'
Requires-Dist: ipython>=8.12.0; extra == 'dev'
Requires-Dist: jupyter>=1.0.0; extra == 'dev'
Requires-Dist: mypy>=1.7.0; extra == 'dev'
Requires-Dist: pytest-cov>=4.1.0; extra == 'dev'
Requires-Dist: pytest>=7.4.0; extra == 'dev'
Requires-Dist: ruff>=0.1.0; extra == 'dev'
Provides-Extra: query
Requires-Dist: pyparsing>=3.1.0; extra == 'query'
Provides-Extra: viz
Requires-Dist: matplotlib>=3.8.0; extra == 'viz'
Requires-Dist: networkx>=3.2.0; extra == 'viz'
Provides-Extra: web
Requires-Dist: fastapi>=0.104.0; extra == 'web'
Requires-Dist: python-multipart>=0.0.21; extra == 'web'
Requires-Dist: uvicorn>=0.24.0; extra == 'web'
